workerflow/__init__.py
workerflow/__main__.py
workerflow/arguments.py
workerflow/entrypoint.py
workerflow/aio/__init__.py
workerflow/aio/policy.py
workerflow/aio/run.py
workerflow/apps/__init__.py
workerflow/apps/master/__init__.py
workerflow/assets/__init__.py
workerflow/logging/__init__.py
workerflow/logging/logging.py
workerflow/logging/formatters/__init__.py
workerflow/logging/formatters/colored.py
workerflow/system/__init__.py
workerflow/system/environ.py
workerflow/types/__init__.py
workerflow/types/override.py
workerflow/types/string/__init__.py
workerflow/types/string/to_boolean.py
workerflow-0.0.1.dist-info/LICENSE
workerflow-0.0.1.dist-info/METADATA
workerflow-0.0.1.dist-info/WHEEL
workerflow-0.0.1.dist-info/entry_points.txt
workerflow-0.0.1.dist-info/top_level.txt
workerflow-0.0.1.dist-info/RECORD
