Metadata-Version: 2.2
Name: workerflow
Version: 0.0.1
Summary: Graph-based Visual Programming core module for workers
Home-page: https://github.com/osom8979/workerflow
Author: zer0
Author-email: osom8979@gmail.com
Maintainer: zer0
Maintainer-email: osom8979@gmail.com
License: MIT License
Project-URL: GitHub: issues, https://github.com/osom8979/workerflow/issues
Project-URL: GitHub: repo, https://github.com/osom8979/workerflow
Classifier: Development Status :: 4 - Beta
Classifier: Framework :: AsyncIO
Classifier: Intended Audience :: Developers
Classifier: Operating System :: OS Independent
Classifier: Programming Language :: Python
Classifier: Programming Language :: Python :: 3.9
Classifier: Topic :: Utilities
Classifier: License :: OSI Approved :: MIT License
Requires-Python: >=3.9
License-File: LICENSE
Requires-Dist: coloredlogs==15.0.1
Requires-Dist: python-dotenv==1.0.1
Requires-Dist: uvloop==0.19.0
Dynamic: requires-dist
